setup.py
lnd/__init__.py
lnd.egg-info/PKG-INFO
lnd.egg-info/SOURCES.txt
lnd.egg-info/dependency_links.txt
lnd.egg-info/not-zip-safe
lnd.egg-info/top_level.txt